unprompted/__init__.py
unprompted/_llm.py
unprompted/_utilities.py
unprompted/_watchers.py
unprompted-0.1.3.dist-info/licenses/LICENSE
unprompted-0.1.3.dist-info/METADATA
unprompted-0.1.3.dist-info/WHEEL
unprompted-0.1.3.dist-info/top_level.txt
unprompted-0.1.3.dist-info/RECORD
