Metadata-Version: 2.4
Name: unprompted
Version: 0.1.3
Summary: An AI-assistant which gives unprompted feedback about code helping you to write better code in Jupyter notebooks
Home-page: https://github.com/haesleinhuepf/unprompted
Author: Robert Haase
Author-email: robert.haase@uni-leipzig.de
Classifier: Programming Language :: Python :: 3
Classifier: License :: OSI Approved :: BSD License
Classifier: Operating System :: OS Independent
Requires-Python: >=3.9
License-File: LICENSE
Dynamic: author
Dynamic: author-email
Dynamic: classifier
Dynamic: description-content-type
Dynamic: home-page
Dynamic: license-file
Dynamic: requires-python
Dynamic: summary
